ios_scroll_wrapper
