Metadata-Version: 2.1
Name: ios-scroll-wrapper
Version: 1.0.3
Summary: Dash IOS Scroll Component
Author: s_matsumoto <s_matsumoto@thinkup-sol.co.jp>
License: MIT
Classifier: Framework :: Dash
License-File: LICENSE
